bigfeat/__init__.py
bigfeat/bigfeat_base.py
bigfeat/local_utils.py
bigfeat-0.1.dist-info/METADATA
bigfeat-0.1.dist-info/WHEEL
bigfeat-0.1.dist-info/top_level.txt
bigfeat-0.1.dist-info/RECORD
