Metadata-Version: 2.1
Name: bigfeat
Version: 0.1
Summary: Automated feature engineering library
Home-page: https://github.com/DataSystemsGroupUT/BigFeat
License: MIT
Keywords: feature engineering,machine learning,automl,feature extraction,feature selection
Requires-Dist: pandas
Requires-Dist: numpy
Requires-Dist: scikit-learn
Requires-Dist: lightgbm
